gpsdclient/__init__.py
gpsdclient/__main__.py
gpsdclient/cli.py
gpsdclient/client.py
gpsdclient-1.3.0.dist-info/entry_points.txt
gpsdclient-1.3.0.dist-info/LICENSE.txt
gpsdclient-1.3.0.dist-info/WHEEL
gpsdclient-1.3.0.dist-info/METADATA
gpsdclient-1.3.0.dist-info/RECORD
