Metadata-Version: 2.1
Name: gpsdclient
Version: 1.3.0
Summary: A simple gpsd client.
Home-page: https://github.com/tfeldmann/gpsdclient
License: MIT
Keywords: gpsd,gps,client,standalone,socket,stream
Author: Thomas Feldmann
Author-email: mail@tfeldmann.de
Requires-Python: >=3.6,<4.0
Classifier: Development Status :: 5 - Production/Stable
Classifier: License :: OSI Approved :: MIT License
Classifier: Operating System :: OS Independent
Classifier: Programming Language :: Python :: 3
Classifier: Programming Language :: Python :: 3.6
Classifier: Programming Language :: Python :: 3.7
Classifier: Programming Language :: Python :: 3.8
Classifier: Programming Language :: Python :: 3.9
Classifier: Programming Language :: Python :: 3.10
Classifier: Topic :: Software Development :: Libraries
Classifier: Topic :: Utilities
Project-URL: Repository, https://github.com/tfeldmann/gpsdclient
